[
  {
    "id": 40241,
    "word": "blind",
    "definition": "Unable to see; sightless; a word that gains force in public speech.",
    "example": "An eye for an eye only ends up making the whole world blind.",
    "partOfSpeech": "adjective",
    "oratorId": 13,
    "complexity": "intermediate",
    "source": "Various writings and speeches (often attributed)",
    "speech": "Young India and public addresses",
    "categories": ["humanities", "inspirational", "legacy"]
  },
  {
    "id": 40242,
    "word": "peace",
    "definition": "Freedom from disturbance; tranquility; a word that gains force in public speech.",
    "example": "There is no path to peace. Peace is the path.",
    "partOfSpeech": "noun",
    "oratorId": 13,
    "complexity": "intermediate",
    "source": "Various",
    "speech": "Public addresses on non-violence",
    "categories": ["democracy", "humanities", "courage"]
  },
  {
    "id": 40243,
    "word": "forgiveness",
    "definition": "The action or process of forgiving or being forgiven",
    "example": "The weak can never forgive. Forgiveness is the attribute of the strong.",
    "partOfSpeech": "noun",
    "oratorId": 13,
    "complexity": "intermediate",
    "source": "Various",
    "speech": "Addresses on non-violence and reconciliation",
    "categories": ["humanities", "inspirational", "legacy"]
  },
  {
    "id": 40244,
    "word": "change",
    "definition": "Make or become different; a word that gains force in public speech.",
    "example": "You must be the change you wish to see in the world.",
    "partOfSpeech": "noun",
    "oratorId": 13,
    "complexity": "intermediate",
    "source": "Various (widely attributed)",
    "speech": "Public teachings",
    "categories": ["humanities", "inspirational", "legacy"]
  },
  {
    "id": 40245,
    "word": "strength",
    "definition": "The quality or state of being physically strong; a word that gains force in public speech.",
    "example": "Strength does not come from physical capacity. It comes from an indomitable will.",
    "partOfSpeech": "noun",
    "oratorId": 13,
    "complexity": "intermediate",
    "source": "Various writings",
    "speech": "On satyagraha and personal discipline",
    "categories": ["humanities", "inspirational", "legacy"]
  },
  {
    "id": 40246,
    "word": "will",
    "definition": "The faculty by which a person decides on and initiates action",
    "example": "Strength does not come from physical capacity. It comes from an indomitable will.",
    "partOfSpeech": "noun",
    "oratorId": 13,
    "complexity": "intermediate",
    "source": "Various writings",
    "speech": "On satyagraha and personal discipline",
    "categories": ["humanities", "inspirational", "legacy"]
  },
  {
    "id": 40247,
    "word": "happiness",
    "definition": "The state of being happy; a word that gains force in public speech.",
    "example": "Happiness is when what you think, what you say, and what you do are in harmony.",
    "partOfSpeech": "noun",
    "oratorId": 13,
    "complexity": "intermediate",
    "source": "Various writings",
    "speech": "On truth (satya) and integrity",
    "categories": ["humanities", "inspirational", "legacy"]
  },
  {
    "id": 40248,
    "word": "harmony",
    "definition": "The combination of simultaneously sounded musical notes to produce a pleasing effect",
    "example": "Happiness is when what you think, what you say, and what you do are in harmony.",
    "partOfSpeech": "noun",
    "oratorId": 13,
    "complexity": "intermediate",
    "source": "Various writings",
    "speech": "On truth (satya) and integrity",
    "categories": ["democracy", "humanities", "courage"]
  },
  {
    "id": 40249,
    "word": "future",
    "definition": "The time or a period of time following the moment of speaking or writing",
    "example": "The future depends on what you do today.",
    "partOfSpeech": "noun",
    "oratorId": 13,
    "complexity": "intermediate",
    "source": "Various",
    "speech": "Public exhortations",
    "categories": ["humanities", "inspirational", "legacy"]
  },
  {
    "id": 40250,
    "word": "violence",
    "definition": "Behavior involving physical force intended to hurt, damage, or kill someone or something",
    "example": "I object to violence because when it appears to do good, the good is only temporary; the evil it does is permanent.",
    "partOfSpeech": "noun",
    "oratorId": 13,
    "complexity": "intermediate",
    "source": "Young India / Harijan",
    "speech": "Writings on satyagraha",
    "categories": ["humanities", "inspirational", "legacy"]
  },
  {
    "id": 40251,
    "word": "error",
    "definition": "A mistake; a word that gains force in public speech.",
    "example": "Error is the hinge of On swaraj (self-rule) and liberty: without it the rest is decoration.",
    "partOfSpeech": "noun",
    "oratorId": 13,
    "complexity": "intermediate",
    "source": "Various",
    "speech": "On swaraj (self-rule) and liberty",
    "categories": ["humanities", "inspirational", "legacy"]
  },
  {
    "id": 40252,
    "word": "Non-violence",
    "definition": "The use of peaceful means, not force, to bring about political or social change",
    "example": "Non-violence is the greatest force at the disposal of mankind.",
    "partOfSpeech": "noun",
    "oratorId": 13,
    "complexity": "intermediate",
    "source": "Young India / Harijan",
    "speech": "Writings on satyagraha",
    "categories": ["humanities", "inspirational", "legacy"]
  },
  {
    "id": 40253,
    "word": "truth",
    "definition": "The quality or state of being true; a word that gains force in public speech.",
    "example": "Truth is the hinge of On truth and courage: without it the rest is decoration.",
    "partOfSpeech": "noun",
    "oratorId": 13,
    "complexity": "intermediate",
    "source": "Various writings",
    "speech": "On truth and courage",
    "categories": ["humanities", "inspirational", "legacy"]
  },
  {
    "id": 40254,
    "word": "greed",
    "definition": "Intense and selfish desire for something, especially wealth, power, or food",
    "example": "Earth provides enough to satisfy every man's needs, but not every man's greed.",
    "partOfSpeech": "noun",
    "oratorId": 13,
    "complexity": "intermediate",
    "source": "Various (widely attributed in his writings on trusteeship and simplicity)",
    "speech": "On economics and simple living",
    "categories": ["leadership", "democracy", "legacy"]
  },
  {
    "id": 40255,
    "word": "darkness",
    "definition": "The partial or total absence of light; a word that gains force in public speech.",
    "example": "In the midst of darkness, light persists.",
    "partOfSpeech": "noun",
    "oratorId": 13,
    "complexity": "intermediate",
    "source": "Various",
    "speech": "On hope during the independence struggle",
    "categories": ["arts", "humanities", "legacy"]
  },
  {
    "id": 40256,
    "word": "light",
    "definition": "The natural agent that stimulates sight and makes things visible",
    "example": "In the midst of darkness, light persists.",
    "partOfSpeech": "noun",
    "oratorId": 13,
    "complexity": "intermediate",
    "source": "Various",
    "speech": "On hope during the independence struggle",
    "categories": ["humanities", "inspirational", "legacy"]
  },
  {
    "id": 40257,
    "word": "path",
    "definition": "A way or track laid down for walking or made by continual treading",
    "example": "There is no path to peace. Peace is the path.",
    "partOfSpeech": "noun",
    "oratorId": 13,
    "complexity": "intermediate",
    "source": "Various",
    "speech": "On non-violence",
    "categories": ["humanities", "inspirational", "legacy"]
  },
  {
    "id": 40258,
    "word": "conviction",
    "definition": "A firmly held belief or opinion; a word that gains force in public speech.",
    "example": "A 'No' uttered from the deepest conviction is better than a 'Yes' merely uttered to please, or worse, to avoid trouble.",
    "partOfSpeech": "noun",
    "oratorId": 13,
    "complexity": "intermediate",
    "source": "Various writings",
    "speech": "On truth and courage",
    "categories": ["leadership"]
  },
  {
    "id": 40259,
    "word": "civilization",
    "definition": "The stage of human social and cultural development and organization that is considered most advanced",
    "example": "Civilization is the hinge of On ethics and civilization: without it the rest is decoration.",
    "partOfSpeech": "noun",
    "oratorId": 13,
    "complexity": "intermediate",
    "source": "Various (often in writings on compassion)",
    "speech": "On ethics and civilization",
    "categories": ["humanities", "inspirational", "legacy"]
  },
  {
    "id": 40260,
    "word": "moral",
    "definition": "Concerned with the principles of right and wrong behavior",
    "example": "The greatness of a nation and its moral progress can be judged by the way its animals are treated.",
    "partOfSpeech": "adjective",
    "oratorId": 13,
    "complexity": "intermediate",
    "source": "Various (often in writings on compassion)",
    "speech": "On ethics and civilization",
    "categories": ["humanities"]
  }
]
